pyrmrf/__init__.py
pyrmrf-1.0.0.dist-info/METADATA
pyrmrf-1.0.0.dist-info/WHEEL
pyrmrf-1.0.0.dist-info/entry_points.txt
pyrmrf-1.0.0.dist-info/licenses/LICENSE
pyrmrf-1.0.0.dist-info/RECORD
